gcp_pubsub_events/__init__.py
gcp_pubsub_events/core/__init__.py
gcp_pubsub_events/core/acknowledgement.py
gcp_pubsub_events/core/client.py
gcp_pubsub_events/core/manager.py
gcp_pubsub_events/core/registry.py
gcp_pubsub_events/core/resources.py
gcp_pubsub_events/decorators/__init__.py
gcp_pubsub_events/decorators/listener.py
gcp_pubsub_events/decorators/subscription.py
gcp_pubsub_events/exceptions/__init__.py
gcp_pubsub_events/exceptions/base.py
gcp_pubsub_events/exceptions/serialization.py
gcp_pubsub_events/exceptions/subscription.py
gcp_pubsub_events/utils/__init__.py
gcp_pubsub_events/utils/serialization.py
gcp_pubsub_events-2.0.0.dist-info/METADATA
gcp_pubsub_events-2.0.0.dist-info/WHEEL
gcp_pubsub_events-2.0.0.dist-info/RECORD
