Metadata-Version: 2.3
Name: gcp-pubsub-events
Version: 2.0.0
Summary: A decorator-based library for handling Google Cloud Pub/Sub messages with FastAPI integration, inspired by Micronaut's @PubSubListener
License: MIT
Keywords: pubsub,google-cloud,fastapi,microservices,event-driven
Author: Your Name
Author-email: shadowrhyder@gmail.com
Requires-Python: >=3.11,<4.0
Classifier: Development Status :: 5 - Production/Stable
Classifier: Framework :: AsyncIO
Classifier: Framework :: FastAPI
Classifier: Intended Audience :: Developers
Classifier: License :: OSI Approved :: MIT License
Classifier: Operating System :: OS Independent
Classifier: Programming Language :: Python :: 3
Classifier: Programming Language :: Python :: 3.11
Classifier: Programming Language :: Python :: 3.12
Classifier: Programming Language :: Python :: 3.13
Classifier: Topic :: Software Development :: Libraries :: Python Modules
Classifier: Topic :: System :: Distributed Computing
Provides-Extra: docs
Requires-Dist: google-cloud-pubsub (>=2.0.0,<3.0.0)
Requires-Dist: protobuf (>=3.19.0,<4.0.0)
Requires-Dist: pydantic (>=2.0.0,<3.0.0)
Requires-Dist: pytz (>=2021.1,<2022.0)
Requires-Dist: six (>=1.16.0,<2.0.0)
Project-URL: Documentation, https://github.com/Executioner1939/gcp-pubsub-events
Project-URL: Homepage, https://github.com/Executioner1939/gcp-pubsub-events
Project-URL: Repository, https://github.com/Executioner1939/gcp-pubsub-events
